max_min_python_heaps/__init__.py
max_min_python_heaps/max_heap.py
max_min_python_heaps/min_heap.py
max_min_python_heaps-0.3.dist-info/METADATA
max_min_python_heaps-0.3.dist-info/WHEEL
max_min_python_heaps-0.3.dist-info/top_level.txt
max_min_python_heaps-0.3.dist-info/RECORD
